pandas2redshift/__init__.py
pandas2redshift/pandas2redshift.py
pandas2redshift-0.0.5.dist-info/METADATA
pandas2redshift-0.0.5.dist-info/WHEEL
pandas2redshift-0.0.5.dist-info/top_level.txt
pandas2redshift-0.0.5.dist-info/RECORD
